LICENSE
MANIFEST.in
README.md
setup.py
mongoenginelite/__init__.py
mongoenginelite/connection.py
mongoenginelite/settings.py
mongoenginelite.egg-info/.DS_Store
mongoenginelite.egg-info/PKG-INFO
mongoenginelite.egg-info/SOURCES.txt
mongoenginelite.egg-info/dependency_links.txt
mongoenginelite.egg-info/requires.txt
mongoenginelite.egg-info/top_level.txt
mongoenginelite/mengine/__init__.py
mongoenginelite/mengine/document.py
mongoenginelite/mongo/__init__.py
mongoenginelite/mongo/collection.py
mongoenginelite/mongo/connection.py
mongoenginelite/mongo/cursor.py
mongoenginelite/mongo/database.py
tests/__init__.py
tests/models.py
tests/test.py