Metadata-Version: 1.1
Name: mongoenginelite
Version: 1.1
Summary: This is a lite version of MongoEngine ORM that persists the information in a JSON file, similar to SQLite to SQL databases
Home-page: https://github.com/lmanzurv/mongo_engine_lite
Author: Laura Manzur
Author-email: lc.manzur@novcat.com.co
License: Apache License
Download-URL: https://github.com/lmanzurv/mongo_engine_lite
Keywords: mongo mongoengine lite
Platform: UNKNOWN
Classifier: License :: OSI Approved :: Academic Free License (AFL)
Classifier: Natural Language :: English
Classifier: Programming Language :: Python :: 2.7
